gitrn/__init__.py
gitrn/make_release_notes.py
gitrn-0.0.2.dist-info/DESCRIPTION.rst
gitrn-0.0.2.dist-info/METADATA
gitrn-0.0.2.dist-info/RECORD
gitrn-0.0.2.dist-info/WHEEL
gitrn-0.0.2.dist-info/entry_points.txt
gitrn-0.0.2.dist-info/metadata.json
gitrn-0.0.2.dist-info/top_level.txt
gitrn-0.0.2.dist-info/zip-safe
